odoo/addons/sale_order_line_date/README.rst
odoo/addons/sale_order_line_date/__init__.py
odoo/addons/sale_order_line_date/__manifest__.py
odoo/addons/sale_order_line_date/i18n/ca.po
odoo/addons/sale_order_line_date/i18n/de.po
odoo/addons/sale_order_line_date/i18n/el_GR.po
odoo/addons/sale_order_line_date/i18n/es.po
odoo/addons/sale_order_line_date/i18n/es_ES.po
odoo/addons/sale_order_line_date/i18n/es_VE.po
odoo/addons/sale_order_line_date/i18n/fi.po
odoo/addons/sale_order_line_date/i18n/fr.po
odoo/addons/sale_order_line_date/i18n/hr.po
odoo/addons/sale_order_line_date/i18n/hr_HR.po
odoo/addons/sale_order_line_date/i18n/hu.po
odoo/addons/sale_order_line_date/i18n/it.po
odoo/addons/sale_order_line_date/i18n/nl.po
odoo/addons/sale_order_line_date/i18n/nl_NL.po
odoo/addons/sale_order_line_date/i18n/pt.po
odoo/addons/sale_order_line_date/i18n/pt_BR.po
odoo/addons/sale_order_line_date/i18n/ro.po
odoo/addons/sale_order_line_date/i18n/sale_order_line_date.pot
odoo/addons/sale_order_line_date/i18n/sk.po
odoo/addons/sale_order_line_date/i18n/sl.po
odoo/addons/sale_order_line_date/i18n/tr.po
odoo/addons/sale_order_line_date/i18n/tr_TR.po
odoo/addons/sale_order_line_date/i18n/vi_VN.po
odoo/addons/sale_order_line_date/i18n/zh_CN.po
odoo/addons/sale_order_line_date/models/__init__.py
odoo/addons/sale_order_line_date/models/sale_order.py
odoo/addons/sale_order_line_date/models/sale_order_line.py
odoo/addons/sale_order_line_date/static/description/icon.png
odoo/addons/sale_order_line_date/tests/__init__.py
odoo/addons/sale_order_line_date/tests/test_sale_order_line_date.py
odoo/addons/sale_order_line_date/views/sale_order_view.xml
odoo11_addon_sale_order_line_date-11.0.1.0.1.dist-info/METADATA
odoo11_addon_sale_order_line_date-11.0.1.0.1.dist-info/WHEEL
odoo11_addon_sale_order_line_date-11.0.1.0.1.dist-info/top_level.txt
odoo11_addon_sale_order_line_date-11.0.1.0.1.dist-info/RECORD
